Pycurl743ZhongwenWendang/README.md
Pycurl743ZhongwenWendang/__init__.py
Pycurl743ZhongwenWendang/__main__.py
Pycurl743ZhongwenWendang/file.epub
Pycurl743ZhongwenWendang/index.html
Pycurl743ZhongwenWendang/css/__init__.py
Pycurl743ZhongwenWendang/css/annotations.css
Pycurl743ZhongwenWendang/css/main.css
Pycurl743ZhongwenWendang/css/normalize.css
Pycurl743ZhongwenWendang/css/popup.css
Pycurl743ZhongwenWendang/font/__init__.py
Pycurl743ZhongwenWendang/font/fontello.eot
Pycurl743ZhongwenWendang/font/fontello.svg
Pycurl743ZhongwenWendang/font/fontello.ttf
Pycurl743ZhongwenWendang/font/fontello.woff
Pycurl743ZhongwenWendang/img/__init__.py
Pycurl743ZhongwenWendang/img/annotator-glyph-sprite.png
Pycurl743ZhongwenWendang/img/annotator-icon-sprite.png
Pycurl743ZhongwenWendang/img/apple-touch-icon.png
Pycurl743ZhongwenWendang/img/cancelfullscreen.png
Pycurl743ZhongwenWendang/img/close.png
Pycurl743ZhongwenWendang/img/fullscreen.png
Pycurl743ZhongwenWendang/img/loader.gif
Pycurl743ZhongwenWendang/img/menu-icon.png
Pycurl743ZhongwenWendang/img/save.png
Pycurl743ZhongwenWendang/img/saved.png
Pycurl743ZhongwenWendang/img/settings-s.png
Pycurl743ZhongwenWendang/img/settings.png
Pycurl743ZhongwenWendang/img/star.png
Pycurl743ZhongwenWendang/js/__init__.py
Pycurl743ZhongwenWendang/js/epub.js
Pycurl743ZhongwenWendang/js/epub.min.js
Pycurl743ZhongwenWendang/js/epub.min.map
Pycurl743ZhongwenWendang/js/hooks.min.js
Pycurl743ZhongwenWendang/js/hooks.min.map
Pycurl743ZhongwenWendang/js/reader.js
Pycurl743ZhongwenWendang/js/reader.js.map
Pycurl743ZhongwenWendang/js/reader.min.js
Pycurl743ZhongwenWendang/js/reader.min.map
Pycurl743ZhongwenWendang/js/hooks/__init__.py
Pycurl743ZhongwenWendang/js/hooks/extensions/__init__.py
Pycurl743ZhongwenWendang/js/hooks/extensions/highlight.js
Pycurl743ZhongwenWendang/js/libs/__init__.py
Pycurl743ZhongwenWendang/js/libs/jquery.min.js
Pycurl743ZhongwenWendang/js/libs/localforage.min.js
Pycurl743ZhongwenWendang/js/libs/screenfull.js
pycurl_7_43_zhongwen_wendang-2024.3.4.0.dist-info/METADATA
pycurl_7_43_zhongwen_wendang-2024.3.4.0.dist-info/WHEEL
pycurl_7_43_zhongwen_wendang-2024.3.4.0.dist-info/entry_points.txt
pycurl_7_43_zhongwen_wendang-2024.3.4.0.dist-info/top_level.txt
pycurl_7_43_zhongwen_wendang-2024.3.4.0.dist-info/RECORD
